Workbook

Sheet LÉEME
A1: PLANTILLA DEL TALLER — Contabilidad, Trazabilidad y Fiscalidad en Bitcoin · U. de las Hespérides · Ed. 2026
A3: 1. | B3: Seis hojas: tres se rellenan a mano (DIARIO, UBICACIONES, PARÁMETROS) y tres se calculan solas (SALDOS, FIFO, CUADRE). No escriba en las automáticas salvo en sus celdas amarillas.
A4: 2. | B4: Las celdas AMARILLAS son las únicas de entrada en las hojas automáticas (fecha de corte, activo de la cola, saldo real declarado, tolerancias, catálogo de activos).
A5: 3. | B5: Orden de trabajo: dé de alta sus UBICACIONES → revise PARÁMETROS (una sola vez) → cargue el DIARIO → cuadre. Regla de secuencia (Unidad 5): cargar → cuadrar → clasificar.
A6: 4. | B6: DIARIO: una línea por movimiento, gravable o no (principio 1: integridad). El Tipo se elige del catálogo cerrado; las ubicaciones, de los desplegables. «EXTERIOR» = fuera del patrimonio propio.
A7: 5. | B7: La comisión va SIEMPRE en su columna, nunca embebida. Convención del taller: se descuenta en la ubicación de ORIGEN (si el origen es EXTERIOR, en la de destino). Véase PARÁMETROS.
A8: 6. | B8: Contravalor EUR solo en operaciones-frontera (compra, venta, permuta, rendimiento, pago), con la fuente de la cotización en Notas. Los movimientos internos no lo llevan.
A9: 7. | B9: Ningún apunte sin justificante: referencia a la carpeta del ejercicio (01–06) o txid. Un apunte sin justificante es una afirmación sin prueba (principio 6).
A10: 8. | B10: No borre ni edite apuntes ya cargados: corrija con un apunte AJUSTE/RECTIFICACIÓN que cite en «Notas / rectifica a» el nº del apunte corregido (principio 7).
A11: 9. | B11: SALDOS: elija la fecha de corte en la celda amarilla. Un saldo en ROJO es un saldo negativo: se vendió o transfirió lo que no consta adquirido («venta sin origen», Unidad 7).
A12: 10. | B12: FIFO: elija el activo de la cola (por defecto BTC). Exige el DIARIO en orden cronológico. La comisión de adquisición en EUR SUMA al coste del lote; la de venta MINORA el valor de transmisión.
A13: 11. | B13: Las columnas rotuladas AUXILIAR (en gris, hoja FIFO) sostienen el cálculo: no las toque ni las borre.
A14: 12. | B14: CUADRE: teclee el «saldo real declarado» que muestra cada exchange/wallet/canal a la fecha de corte. Semáforo: verde OK · ámbar REVISAR · rojo ERROR, con tolerancias configurables en PARÁMETROS.
... A17: 15. | B17: Remisiones: método U4 · carga y cuadre U5 · catálogo y FIFO U6 · depuración U7 · eventos U8 (Anexo B) · IRPF U9 (Anexo C) · cierre U10 (Anexo D).
A19: ADVERTENCIA: las filas marcadas «EJEMPLO — borrar» (en DIARIO, UBICACIONES y CUADRE) son las de la Tabla 4 del manual. Bórrelas antes de cargar datos reales.

Sheet DIARIO
A1: Nº | B1: Fecha y hora | C1: Tipo | D1: Ubicación origen | E1: Ubicación destino | F1: Activo salida / cantidad | H1: Activo entrada / cantidad | J1: Comisión / activo | L1: Contravalor EUR | M1: Justificante | N1: Notas / rectifica a
F2: Activo | G2: Cantidad | H2: Activo | I2: Cantidad | J2: Cantidad | K2: Activo
A3: 2026-001 | B3: 46038.445 | C3: COMPRA | D3: Exchange-A | E3: Exchange-A | F3: EUR | G3: 20000 | H3: BTC | I3: 0.5 | J3: 30 | K3: EUR | L3: 20000 | M3: 01-adquisiciones/orden-exchA-2026-001.pdf | N3: EJEMPLO — borrar · cotización: Exchange-A
A4: 2026-002 | B4: 46056.764 | C4: TRANSFERENCIA | D4: Exchange-A | E4: Wallet-Fría | F4: BTC | G4: 0.3 | H4: BTC | I4: 0.3 | J4: 0.0002 | K4: BTC | M4: 02-transferencias/txid-a1b2c3.txt | N4: EJEMPLO — borrar · sin frontera: sin contravalor
A5: 2026-003 | B5: 46082.383 | C5: RENDIMIENTO | D5: EXTERIOR | E5: Exchange-A | H5: BTC | I5: 0.05 | L5: 130 | M5: 04-rendimientos/staking-2026-03.pdf | N5: EJEMPLO — borrar · cotización del día (fuente citada)

Sheet UBICACIONES
A1: UBICACIONES — alta de cada exchange, wallet o canal (principio 3: todo saldo tiene ubicación)
A2: Una fila por ubicación. SALDOS y CUADRE cubren las 10 primeras. La columna H alimenta los desplegables del DIARIO (no tocar).
A3: Nombre | B3: Tipo (exchange / wallet / canal) | C3: KYC (sí / no) | D3: Fecha de alta | E3: Fecha de cierre | F3: Notas | H3: Lista desplegables (no tocar)
A4: Exchange-A | B4: exchange | C4: sí | D4: 46032 | F4: EJEMPLO — borrar | H4: EXTERIOR
A5: Wallet-Fría | B5: wallet | C5: no | D5: 46042 | F5: EJEMPLO — borrar | H5: =IF($A4="","",$A4) -> Exchange-A
A6: Canal-LN | B6: canal | C6: no | D6: 46068 | F6: EJEMPLO — borrar | H6: =IF($A5="","",$A5) -> Wallet-Fría
H7: =IF($A6="","",$A6) -> Canal-LN
H8: =IF($A7="","",$A7)
H9: =IF($A8="","",$A8)
H10: =IF($A9="","",$A9)
H11: =IF($A10="","",$A10)
H12: =IF($A11="","",$A11)
H13: =IF($A12="","",$A12)
H14: =IF($A13="","",$A13)
H15: =IF($A14="","",$A14)
H16: =IF($A15="","",$A15)
H17: =IF($A16="","",$A16)
H18: =IF($A17="","",$A17)
... H34: =IF($A33="","",$A33)

Sheet PARÁMETROS
A1: PARÁMETROS — catálogo cerrado de tipos y convenciones del taller (se rellena UNA vez)
A3: 1. Catálogo CERRADO de tipos de operación (Unidad 6, Tabla 7). La columna Tipo del DIARIO solo admite estos once valores.
A4: Tipo | B4: ¿Cuadra? (¿salida y entrada equivalentes?) | C4: ¿Alteración patrimonial? | D4: ¿Abre lote FIFO? | E4: ¿Consume lote FIFO? | F4: Calificación fiscal (remisión al Manual de Fiscalidad) | G4: Nota contable
A5: COMPRA | B5: Sí | C5: No (cambia composición) | D5: Sí | E5: No | F5: Sin hecho imponible; fija lote FIFO (T3) | G5: Comisión de compra: se suma al coste del lote
A6: VENTA | B6: Sí | C6: Sí | D6: No | E6: Sí | F6: Ganancia/pérdida patrimonial, base del ahorro (T2-T3) | G6: Comisión de venta: minora el valor de transmisión
A7: PERMUTA | B7: Sí | C7: Sí | D7: Sí | E7: Sí | F7: Alteración patrimonial: se transmite lo entregado (T3) | G7: El activo recibido nace como lote nuevo a valor de mercado
A8: TRANSFERENCIA | B8: Sí (mismo activo ±comisión) | C8: No | D8: No | E8: No | F8: Sin hecho imponible | G8: La comisión de red sí sale del patrimonio: se registra siempre (T3)
A9: RENDIMIENTO | B9: No (entra sin salir) | C9: Sí (entra valor) | D9: Sí | E9: No | F9: RCM art. 25.2 LIRPF — DGT V1766-22 y V0612-26 (T3) | G9: El contravalor del día es ingreso y, a la vez, coste del lote nuevo
A10: MINERÍA | B10: No (entra sin salir) | C10: Sí (entra valor) | D10: Sí | E10: No | F10: Rendimiento de actividad económica (T3) | G10: Igual que RENDIMIENTO en lo contable; distinta casilla en Renta
A11: AIRDROP | B11: No (entra sin salir) | C11: Sí (entra valor) | D11: Sí | E11: No | F11: Ganancia patrimonial, base general — DGT 0018-23, no vinculante (T2) | G11: Lote nuevo a valor de mercado del día
A12: PAGO | B12: Sí (sale cripto, entra bien/servicio) | C12: Sí | D12: No | E12: Sí | F12: Transmisión: alteración patrimonial (T3) | G12: Como una venta cuyo «precio» es la factura del bien recibido
A13: PÉRDIDA | B13: No (solo salida) | C13: Sí | D13: No | E13: Sí | F13: Pérdida patrimonial condicionada a requisitos y prueba — dualidad de criterios DGT (T2) | G13: Registrar siempre; deducir solo con el expediente que T2 exige
A14: DONACIÓN | B14: Según sentido | C14: Sí | D14: Según (recibida: abre) | E14: Según (entregada: consume) | F14: Entregada: alteración en el donante (con límites); recibida: ISD (T1-T2) | G14: Documento de donación como justificante; fija valor y fecha del receptor
A15: AJUSTE/RECTIFICACIÓN | B15: Según el caso | C15: Según el caso | D15: Según el caso | E15: Según el caso | F15: — | G15: Solo con referencia al apunte corregido y nota de causa (principio 7)
A16: Nota: los valores «Según…» exigen decisión manual; SALDOS y FIFO solo automatizan los tipos con «Sí»/«No» inequívoco. Una DONACIÓN o un AJUSTE se acompañan siempre de nota explicativa.
A18: 2. Catálogo de activos (alimenta SALDOS, CUADRE y los desplegables de activo). Añada los suyos en las celdas amarillas.
A19: Activo
A20: BTC
A21: EUR
A26: 3. Convenciones del taller (Unidad 5) y tolerancias del CUADRE (celdas amarillas: configurables).
A27: Zona horaria | B27: Todo el DIARIO en hora local española; las fuentes UTC se convierten al cargar y se anota la conversión.
A28: Decimales | B28: BTC siempre con 8 decimales (0,00000350). Cuidado con los CSV anglosajones: punto decimal ≠ separador de miles.
A29: Comisiones | B29: Siempre separadas, en su columna. Convención: la comisión se descuenta en la ubicación de ORIGEN; si el origen es EXTERIOR, en la de destino.
A30: Identidad de los activos | B30: BTC es BTC; el «BTC» de un exchange, el WBTC de otra cadena y un saldo Lightning se registran como activos o ubicaciones distintos.
A31: Criterio de consumo | B31: FIFO sobre cola ÚNICA global por activo, sin distinguir ubicación (criterio administrativo vigente: V0525-25, V0491-26).
A32: Tolerancia VERDE del cuadre (|dif| ≤ → OK) | B32: 1e-08
A33: Tolerancia ÁMBAR del cuadre (|dif| ≤ → REVISAR; mayor → ERROR) | B33: 0.001

Sheet SALDOS
A1: SALDOS — se calcula solo. Saldo por activo y ubicación a la fecha de corte
A2: Fecha de corte: | B2: 46387 | C2: ← editable: cualquier fecha (Unidad 7: la elección de fecha acota el descuadre en el tiempo)
A3: Saldo = entradas − salidas − comisiones, por ubicación (Unidad 5). ROJO = saldo negativo: venta o salida sin origen registrado (Unidad 7). Cubre las 10 primeras UBICACIONES × 5 activos del catálogo.
A4: Ubicación | B4: Activo | C4: Entradas | D4: Salidas | E4: Comisiones | F4: Saldo
A5: =IF(OR(T(INDEX(UBICACIONES!$A$4:$A$13,INT((ROW()-5)/5)+1))="",T(INDEX(PARÁMETROS!$A$20:$A$24,MOD(ROW()-5,5)+1))=""),"",T(INDEX(UBICACIONES!$A$4:$A$13,INT((ROW()-5)/5)+1))) -> Exchange-A | B5: =IF(OR(T(INDEX(UBICACIONES!$A$4:$A$13,INT((ROW()-5)/5)+1))="",T(INDEX(PARÁMETROS!$A$20:$A$24,MOD(ROW()-5,5)+1))=""),"",T(INDEX(PARÁMETROS!$A$20:$A$24,MOD(ROW()-5,5)+1))) -> BTC | C5: =IF($A5="","",SUMIFS(DIARIO!$I$3:$I$102,DIARIO!$E$3:$E$102,$A5,DIARIO!$H$3:$H$102,$B5,DIARIO!$B$3:$B$102,"<"&($B$2+1))) -> 0.55 | D5: =IF($A5="","",SUMIFS(DIARIO!$G$3:$G$102,DIARIO!$D$3:$D$102,$A5,DIARIO!$F$3:$F$102,$B5,DIARIO!$B$3:$B$102,"<"&($B$2+1))) -> 0.3 | E5: =IF($A5="","",SUMIFS(DIARIO!$J$3:$J$102,DIARIO!$D$3:$D$102,$A5,DIARIO!$K$3:$K$102,$B5,DIARIO!$B$3:$B$102,"<"&($B$2+1))+SUMIFS(DIARIO!$J$3:$J$102,DIARIO!$D$3:$D$102,"EXTERIOR",DIARIO!$E$3:$E$102,$A5,DIARIO!$K$3:$K$102,$B5,DIARIO!$B$3:$B$102,"<"&($B$2+1))) -> 0.0002 | F5: =IF($A5="","",C5-D5-E5) -> 0.2498
A6: =IF(OR(T(INDEX(UBICACIONES!$A$4:$A$13,INT((ROW()-5)/5)+1))="",T(INDEX(PARÁMETROS!$A$20:$A$24,MOD(ROW()-5,5)+1))=""),"",T(INDEX(UBICACIONES!$A$4:$A$13,INT((ROW()-5)/5)+1))) -> Exchange-A | B6: =IF(OR(T(INDEX(UBICACIONES!$A$4:$A$13,INT((ROW()-5)/5)+1))="",T(INDEX(PARÁMETROS!$A$20:$A$24,MOD(ROW()-5,5)+1))=""),"",T(INDEX(PARÁMETROS!$A$20:$A$24,MOD(ROW()-5,5)+1))) -> EUR | C6: =IF($A6="","",SUMIFS(DIARIO!$I$3:$I$102,DIARIO!$E$3:$E$102,$A6,DIARIO!$H$3:$H$102,$B6,DIARIO!$B$3:$B$102,"<"&($B$2+1))) -> 0 | D6: =IF($A6="","",SUMIFS(DIARIO!$G$3:$G$102,DIARIO!$D$3:$D$102,$A6,DIARIO!$F$3:$F$102,$B6,DIARIO!$B$3:$B$102,"<"&($B$2+1))) -> 20000 | E6: =IF($A6="","",SUMIFS(DIARIO!$J$3:$J$102,DIARIO!$D$3:$D$102,$A6,DIARIO!$K$3:$K$102,$B6,DIARIO!$B$3:$B$102,"<"&($B$2+1))+SUMIFS(DIARIO!$J$3:$J$102,DIARIO!$D$3:$D$102,"EXTERIOR",DIARIO!$E$3:$E$102,$A6,DIARIO!$K$3:$K$102,$B6,DIARIO!$B$3:$B$102,"<"&($B$2+1))) -> 30 | F6: =IF($A6="","",C6-D6-E6) -> -20030
A7: =IF(OR(T(INDEX(UBICACIONES!$A$4:$A$13,INT((ROW()-5)/5)+1))="",T(INDEX(PARÁMETROS!$A$20:$A$24,MOD(ROW()-5,5)+1))=""),"",T(INDEX(UBICACIONES!$A$4:$A$13,INT((ROW()-5)/5)+1))) | B7: =IF(OR(T(INDEX(UBICACIONES!$A$4:$A$13,INT((ROW()-5)/5)+1))="",T(INDEX(PARÁMETROS!$A$20:$A$24,MOD(ROW()-5,5)+1))=""),"",T(INDEX(PARÁMETROS!$A$20:$A$24,MOD(ROW()-5,5)+1))) | C7: =IF($A7="","",SUMIFS(DIARIO!$I$3:$I$102,DIARIO!$E$3:$E$102,$A7,DIARIO!$H$3:$H$102,$B7,DIARIO!$B$3:$B$102,"<"&($B$2+1))) | D7: =IF($A7="","",SUMIFS(DIARIO!$G$3:$G$102,DIARIO!$D$3:$D$102,$A7,DIARIO!$F$3:$F$102,$B7,DIARIO!$B$3:$B$102,"<"&($B$2+1))) | E7: =IF($A7="","",SUMIFS(DIARIO!$J$3:$J$102,DIARIO!$D$3:$D$102,$A7,DIARIO!$K$3:$K$102,$B7,DIARIO!$B$3:$B$102,"<"&($B$2+1))+SUMIFS(DIARIO!$J$3:$J$102,DIARIO!$D$3:$D$102,"EXTERIOR",DIARIO!$E$3:$E$102,$A7,DIARIO!$K$3:$K$102,$B7,DIARIO!$B$3:$B$102,"<"&($B$2+1))) | F7: =IF($A7="","",C7-D7-E7)
A8: =IF(OR(T(INDEX(UBICACIONES!$A$4:$A$13,INT((ROW()-5)/5)+1))="",T(INDEX(PARÁMETROS!$A$20:$A$24,MOD(ROW()-5,5)+1))=""),"",T(INDEX(UBICACIONES!$A$4:$A$13,INT((ROW()-5)/5)+1))) | B8: =IF(OR(T(INDEX(UBICACIONES!$A$4:$A$13,INT((ROW()-5)/5)+1))="",T(INDEX(PARÁMETROS!$A$20:$A$24,MOD(ROW()-5,5)+1))=""),"",T(INDEX(PARÁMETROS!$A$20:$A$24,MOD(ROW()-5,5)+1))) | C8: =IF($A8="","",SUMIFS(DIARIO!$I$3:$I$102,DIARIO!$E$3:$E$102,$A8,DIARIO!$H$3:$H$102,$B8,DIARIO!$B$3:$B$102,"<"&($B$2+1))) | D8: =IF($A8="","",SUMIFS(DIARIO!$G$3:$G$102,DIARIO!$D$3:$D$102,$A8,DIARIO!$F$3:$F$102,$B8,DIARIO!$B$3:$B$102,"<"&($B$2+1))) | E8: =IF($A8="","",SUMIFS(DIARIO!$J$3:$J$102,DIARIO!$D$3:$D$102,$A8,DIARIO!$K$3:$K$102,$B8,DIARIO!$B$3:$B$102,"<"&($B$2+1))+SUMIFS(DIARIO!$J$3:$J$102,DIARIO!$D$3:$D$102,"EXTERIOR",DIARIO!$E$3:$E$102,$A8,DIARIO!$K$3:$K$102,$B8,DIARIO!$B$3:$B$102,"<"&($B$2+1))) | F8: =IF($A8="","",C8-D8-E8)
A9: =IF(OR(T(INDEX(UBICACIONES!$A$4:$A$13,INT((ROW()-5)/5)+1))="",T(INDEX(PARÁMETROS!$A$20:$A$24,MOD(ROW()-5,5)+1))=""),"",T(INDEX(UBICACIONES!$A$4:$A$13,INT((ROW()-5)/5)+1))) | B9: =IF(OR(T(INDEX(UBICACIONES!$A$4:$A$13,INT((ROW()-5)/5)+1))="",T(INDEX(PARÁMETROS!$A$20:$A$24,MOD(ROW()-5,5)+1))=""),"",T(INDEX(PARÁMETROS!$A$20:$A$24,MOD(ROW()-5,5)+1))) | C9: =IF($A9="","",SUMIFS(DIARIO!$I$3:$I$102,DIARIO!$E$3:$E$102,$A9,DIARIO!$H$3:$H$102,$B9,DIARIO!$B$3:$B$102,"<"&($B$2+1))) | D9: =IF($A9="","",SUMIFS(DIARIO!$G$3:$G$102,DIARIO!$D$3:$D$102,$A9,DIARIO!$F$3:$F$102,$B9,DIARIO!$B$3:$B$102,"<"&($B$2+1))) | E9: =IF($A9="","",SUMIFS(DIARIO!$J$3:$J$102,DIARIO!$D$3:$D$102,$A9,DIARIO!$K$3:$K$102,$B9,DIARIO!$B$3:$B$102,"<"&($B$2+1))+SUMIFS(DIARIO!$J$3:$J$102,DIARIO!$D$3:$D$102,"EXTERIOR",DIARIO!$E$3:$E$102,$A9,DIARIO!$K$3:$K$102,$B9,DIARIO!$B$3:$B$102,"<"&($B$2+1))) | F9: =IF($A9="","",C9-D9-E9)
A10: =IF(OR(T(INDEX(UBICACIONES!$A$4:$A$13,INT((ROW()-5)/5)+1))="",T(INDEX(PARÁMETROS!$A$20:$A$24,MOD(ROW()-5,5)+1))=""),"",T(INDEX(UBICACIONES!$A$4:$A$13,INT((ROW()-5)/5)+1))) -> Wallet-Fría | B10: =IF(OR(T(INDEX(UBICACIONES!$A$4:$A$13,INT((ROW()-5)/5)+1))="",T(INDEX(PARÁMETROS!$A$20:$A$24,MOD(ROW()-5,5)+1))=""),"",T(INDEX(PARÁMETROS!$A$20:$A$24,MOD(ROW()-5,5)+1))) -> BTC | C10: =IF($A10="","",SUMIFS(DIARIO!$I$3:$I$102,DIARIO!$E$3:$E$102,$A10,DIARIO!$H$3:$H$102,$B10,DIARIO!$B$3:$B$102,"<"&($B$2+1))) -> 0.3 | D10: =IF($A10="","",SUMIFS(DIARIO!$G$3:$G$102,DIARIO!$D$3:$D$102,$A10,DIARIO!$F$3:$F$102,$B10,DIARIO!$B$3:$B$102,"<"&($B$2+1))) -> 0 | E10: =IF($A10="","",SUMIFS(DIARIO!$J$3:$J$102,DIARIO!$D$3:$D$102,$A10,DIARIO!$K$3:$K$102,$B10,DIARIO!$B$3:$B$102,"<"&($B$2+1))+SUMIFS(DIARIO!$J$3:$J$102,DIARIO!$D$3:$D$102,"EXTERIOR",DIARIO!$E$3:$E$102,$A10,DIARIO!$K$3:$K$102,$B10,DIARIO!$B$3:$B$102,"<"&($B$2+1))) -> 0 | F10: =IF($A10="","",C10-D10-E10) -> 0.3
A11: =IF(OR(T(INDEX(UBICACIONES!$A$4:$A$13,INT((ROW()-5)/5)+1))="",T(INDEX(PARÁMETROS!$A$20:$A$24,MOD(ROW()-5,5)+1))=""),"",T(INDEX(UBICACIONES!$A$4:$A$13,INT((ROW()-5)/5)+1))) -> Wallet-Fría | B11: =IF(OR(T(INDEX(UBICACIONES!$A$4:$A$13,INT((ROW()-5)/5)+1))="",T(INDEX(PARÁMETROS!$A$20:$A$24,MOD(ROW()-5,5)+1))=""),"",T(INDEX(PARÁMETROS!$A$20:$A$24,MOD(ROW()-5,5)+1))) -> EUR | C11: =IF($A11="","",SUMIFS(DIARIO!$I$3:$I$102,DIARIO!$E$3:$E$102,$A11,DIARIO!$H$3:$H$102,$B11,DIARIO!$B$3:$B$102,"<"&($B$2+1))) -> 0 | D11: =IF($A11="","",SUMIFS(DIARIO!$G$3:$G$102,DIARIO!$D$3:$D$102,$A11,DIARIO!$F$3:$F$102,$B11,DIARIO!$B$3:$B$102,"<"&($B$2+1))) -> 0 | E11: =IF($A11="","",SUMIFS(DIARIO!$J$3:$J$102,DIARIO!$D$3:$D$102,$A11,DIARIO!$K$3:$K$102,$B11,DIARIO!$B$3:$B$102,"<"&($B$2+1))+SUMIFS(DIARIO!$J$3:$J$102,DIARIO!$D$3:$D$102,"EXTERIOR",DIARIO!$E$3:$E$102,$A11,DIARIO!$K$3:$K$102,$B11,DIARIO!$B$3:$B$102,"<"&($B$2+1))) -> 0 | F11: =IF($A11="","",C11-D11-E11) -> 0
A12: =IF(OR(T(INDEX(UBICACIONES!$A$4:$A$13,INT((ROW()-5)/5)+1))="",T(INDEX(PARÁMETROS!$A$20:$A$24,MOD(ROW()-5,5)+1))=""),"",T(INDEX(UBICACIONES!$A$4:$A$13,INT((ROW()-5)/5)+1))) | B12: =IF(OR(T(INDEX(UBICACIONES!$A$4:$A$13,INT((ROW()-5)/5)+1))="",T(INDEX(PARÁMETROS!$A$20:$A$24,MOD(ROW()-5,5)+1))=""),"",T(INDEX(PARÁMETROS!$A$20:$A$24,MOD(ROW()-5,5)+1))) | C12: =IF($A12="","",SUMIFS(DIARIO!$I$3:$I$102,DIARIO!$E$3:$E$102,$A12,DIARIO!$H$3:$H$102,$B12,DIARIO!$B$3:$B$102,"<"&($B$2+1))) | D12: =IF($A12="","",SUMIFS(DIARIO!$G$3:$G$102,DIARIO!$D$3:$D$102,$A12,DIARIO!$F$3:$F$102,$B12,DIARIO!$B$3:$B$102,"<"&($B$2+1))) | E12: =IF($A12="","",SUMIFS(DIARIO!$J$3:$J$102,DIARIO!$D$3:$D$102,$A12,DIARIO!$K$3:$K$102,$B12,DIARIO!$B$3:$B$102,"<"&($B$2+1))+SUMIFS(DIARIO!$J$3:$J$102,DIARIO!$D$3:$D$102,"EXTERIOR",DIARIO!$E$3:$E$102,$A12,DIARIO!$K$3:$K$102,$B12,DIARIO!$B$3:$B$102,"<"&($B$2+1))) | F12: =IF($A12="","",C12-D12-E12)
A13: =IF(OR(T(INDEX(UBICACIONES!$A$4:$A$13,INT((ROW()-5)/5)+1))="",T(INDEX(PARÁMETROS!$A$20:$A$24,MOD(ROW()-5,5)+1))=""),"",T(INDEX(UBICACIONES!$A$4:$A$13,INT((ROW()-5)/5)+1))) | B13: =IF(OR(T(INDEX(UBICACIONES!$A$4:$A$13,INT((ROW()-5)/5)+1))="",T(INDEX(PARÁMETROS!$A$20:$A$24,MOD(ROW()-5,5)+1))=""),"",T(INDEX(PARÁMETROS!$A$20:$A$24,MOD(ROW()-5,5)+1))) | C13: =IF($A13="","",SUMIFS(DIARIO!$I$3:$I$102,DIARIO!$E$3:$E$102,$A13,DIARIO!$H$3:$H$102,$B13,DIARIO!$B$3:$B$102,"<"&($B$2+1))) | D13: =IF($A13="","",SUMIFS(DIARIO!$G$3:$G$102,DIARIO!$D$3:$D$102,$A13,DIARIO!$F$3:$F$102,$B13,DIARIO!$B$3:$B$102,"<"&($B$2+1))) | E13: =IF($A13="","",SUMIFS(DIARIO!$J$3:$J$102,DIARIO!$D$3:$D$102,$A13,DIARIO!$K$3:$K$102,$B13,DIARIO!$B$3:$B$102,"<"&($B$2+1))+SUMIFS(DIARIO!$J$3:$J$102,DIARIO!$D$3:$D$102,"EXTERIOR",DIARIO!$E$3:$E$102,$A13,DIARIO!$K$3:$K$102,$B13,DIARIO!$B$3:$B$102,"<"&($B$2+1))) | F13: =IF($A13="","",C13-D13-E13)
A14: =IF(OR(T(INDEX(UBICACIONES!$A$4:$A$13,INT((ROW()-5)/5)+1))="",T(INDEX(PARÁMETROS!$A$20:$A$24,MOD(ROW()-5,5)+1))=""),"",T(INDEX(UBICACIONES!$A$4:$A$13,INT((ROW()-5)/5)+1))) | B14: =IF(OR(T(INDEX(UBICACIONES!$A$4:$A$13,INT((ROW()-5)/5)+1))="",T(INDEX(PARÁMETROS!$A$20:$A$24,MOD(ROW()-5,5)+1))=""),"",T(INDEX(PARÁMETROS!$A$20:$A$24,MOD(ROW()-5,5)+1))) | C14: =IF($A14="","",SUMIFS(DIARIO!$I$3:$I$102,DIARIO!$E$3:$E$102,$A14,DIARIO!$H$3:$H$102,$B14,DIARIO!$B$3:$B$102,"<"&($B$2+1))) | D14: =IF($A14="","",SUMIFS(DIARIO!$G$3:$G$102,DIARIO!$D$3:$D$102,$A14,DIARIO!$F$3:$F$102,$B14,DIARIO!$B$3:$B$102,"<"&($B$2+1))) | E14: =IF($A14="","",SUMIFS(DIARIO!$J$3:$J$102,DIARIO!$D$3:$D$102,$A14,DIARIO!$K$3:$K$102,$B14,DIARIO!$B$3:$B$102,"<"&($B$2+1))+SUMIFS(DIARIO!$J$3:$J$102,DIARIO!$D$3:$D$102,"EXTERIOR",DIARIO!$E$3:$E$102,$A14,DIARIO!$K$3:$K$102,$B14,DIARIO!$B$3:$B$102,"<"&($B$2+1))) | F14: =IF($A14="","",C14-D14-E14)
A15: =IF(OR(T(INDEX(UBICACIONES!$A$4:$A$13,INT((ROW()-5)/5)+1))="",T(INDEX(PARÁMETROS!$A$20:$A$24,MOD(ROW()-5,5)+1))=""),"",T(INDEX(UBICACIONES!$A$4:$A$13,INT((ROW()-5)/5)+1))) -> Canal-LN | B15: =IF(OR(T(INDEX(UBICACIONES!$A$4:$A$13,INT((ROW()-5)/5)+1))="",T(INDEX(PARÁMETROS!$A$20:$A$24,MOD(ROW()-5,5)+1))=""),"",T(INDEX(PARÁMETROS!$A$20:$A$24,MOD(ROW()-5,5)+1))) -> BTC | C15: =IF($A15="","",SUMIFS(DIARIO!$I$3:$I$102,DIARIO!$E$3:$E$102,$A15,DIARIO!$H$3:$H$102,$B15,DIARIO!$B$3:$B$102,"<"&($B$2+1))) -> 0 | D15: =IF($A15="","",SUMIFS(DIARIO!$G$3:$G$102,DIARIO!$D$3:$D$102,$A15,DIARIO!$F$3:$F$102,$B15,DIARIO!$B$3:$B$102,"<"&($B$2+1))) -> 0 | E15: =IF($A15="","",SUMIFS(DIARIO!$J$3:$J$102,DIARIO!$D$3:$D$102,$A15,DIARIO!$K$3:$K$102,$B15,DIARIO!$B$3:$B$102,"<"&($B$2+1))+SUMIFS(DIARIO!$J$3:$J$102,DIARIO!$D$3:$D$102,"EXTERIOR",DIARIO!$E$3:$E$102,$A15,DIARIO!$K$3:$K$102,$B15,DIARIO!$B$3:$B$102,"<"&($B$2+1))) -> 0 | F15: =IF($A15="","",C15-D15-E15) -> 0
A16: =IF(OR(T(INDEX(UBICACIONES!$A$4:$A$13,INT((ROW()-5)/5)+1))="",T(INDEX(PARÁMETROS!$A$20:$A$24,MOD(ROW()-5,5)+1))=""),"",T(INDEX(UBICACIONES!$A$4:$A$13,INT((ROW()-5)/5)+1))) -> Canal-LN | B16: =IF(OR(T(INDEX(UBICACIONES!$A$4:$A$13,INT((ROW()-5)/5)+1))="",T(INDEX(PARÁMETROS!$A$20:$A$24,MOD(ROW()-5,5)+1))=""),"",T(INDEX(PARÁMETROS!$A$20:$A$24,MOD(ROW()-5,5)+1))) -> EUR | C16: =IF($A16="","",SUMIFS(DIARIO!$I$3:$I$102,DIARIO!$E$3:$E$102,$A16,DIARIO!$H$3:$H$102,$B16,DIARIO!$B$3:$B$102,"<"&($B$2+1))) -> 0 | D16: =IF($A16="","",SUMIFS(DIARIO!$G$3:$G$102,DIARIO!$D$3:$D$102,$A16,DIARIO!$F$3:$F$102,$B16,DIARIO!$B$3:$B$102,"<"&($B$2+1))) -> 0 | E16: =IF($A16="","",SUMIFS(DIARIO!$J$3:$J$102,DIARIO!$D$3:$D$102,$A16,DIARIO!$K$3:$K$102,$B16,DIARIO!$B$3:$B$102,"<"&($B$2+1))+SUMIFS(DIARIO!$J$3:$J$102,DIARIO!$D$3:$D$102,"EXTERIOR",DIARIO!$E$3:$E$102,$A16,DIARIO!$K$3:$K$102,$B16,DIARIO!$B$3:$B$102,"<"&($B$2+1))) -> 0 | F16: =IF($A16="","",C16-D16-E16) -> 0
... A54: =IF(OR(T(INDEX(UBICACIONES!$A$4:$A$13,INT((ROW()-5)/5)+1))="",T(INDEX(PARÁMETROS!$A$20:$A$24,MOD(ROW()-5,5)+1))=""),"",T(INDEX(UBICACIONES!$A$4:$A$13,INT((ROW()-5)/5)+1))) | B54: =IF(OR(T(INDEX(UBICACIONES!$A$4:$A$13,INT((ROW()-5)/5)+1))="",T(INDEX(PARÁMETROS!$A$20:$A$24,MOD(ROW()-5,5)+1))=""),"",T(INDEX(PARÁMETROS!$A$20:$A$24,MOD(ROW()-5,5)+1))) | C54: =IF($A54="","",SUMIFS(DIARIO!$I$3:$I$102,DIARIO!$E$3:$E$102,$A54,DIARIO!$H$3:$H$102,$B54,DIARIO!$B$3:$B$102,"<"&($B$2+1))) | D54: =IF($A54="","",SUMIFS(DIARIO!$G$3:$G$102,DIARIO!$D$3:$D$102,$A54,DIARIO!$F$3:$F$102,$B54,DIARIO!$B$3:$B$102,"<"&($B$2+1))) | E54: =IF($A54="","",SUMIFS(DIARIO!$J$3:$J$102,DIARIO!$D$3:$D$102,$A54,DIARIO!$K$3:$K$102,$B54,DIARIO!$B$3:$B$102,"<"&($B$2+1))+SUMIFS(DIARIO!$J$3:$J$102,DIARIO!$D$3:$D$102,"EXTERIOR",DIARIO!$E$3:$E$102,$A54,DIARIO!$K$3:$K$102,$B54,DIARIO!$B$3:$B$102,"<"&($B$2+1))) | F54: =IF($A54="","",C54-D54-E54)

Sheet FIFO
A1: FIFO — se calcula solo. Cola ÚNICA de lotes del activo elegido (Unidad 6): adquisiciones que abren lote y consumos por transmisión
A2: Activo de la cola: | B2: BTC | C2: ← editable. Requiere el DIARIO en orden cronológico. Cada fila de aquí refleja la fila del DIARIO de igual orden (fila 7 ↔ apunte 1).
A3: La comisión de adquisición en EUR SUMA al coste del lote; la comisión de venta en EUR MINORA el valor de transmisión (Unidad 6). Un consumo que abarca varios lotes toma su coste de los lotes más antiguos (columna «Consumido»). Columnas AUXILIAR (R–U): sostienen el cálculo, no tocar.
A4: Total adquirido: | B4: =SUM($C$7:$C$106) -> 0.55 | D4: Total consumido: | E4: =SUM($L$7:$L$106) -> 0 | F4: Restante en cola: | G4: =B4-E4 -> 0.55 | J4: Coste del restante (EUR): | L4: =SUM($D$7:$D$106)-SUM($N$7:$N$106) -> 20160 | N4: Resultado transmisiones (EUR): | P4: =SUM($P$7:$P$106) -> 0
A5: LOTES — adquisiciones que abren lote (COMPRA, PERMUTA recibida, RENDIMIENTO, MINERÍA, AIRDROP) | J5: TRANSMISIONES — consumos FIFO (VENTA, PERMUTA entregada, PAGO, PÉRDIDA) | R5: AUXILIAR — no tocar
A6: Nº apunte | B6: Fecha | C6: Cantidad | D6: Coste total (EUR) | E6: Coste unitario (EUR) | F6: Acumulado | G6: Consumido | H6: Restante | J6: Nº apunte | K6: Fecha | L6: Cantidad | M6: Consumo acumulado | N6: Coste FIFO (EUR) | O6: Valor transmisión neto (EUR) | P6: Ganancia / Pérdida (EUR) | R6: ¿Abre lote? | S6: ¿Consume? | T6: Acum. adq. | U6: Acum. cons.
A7: =IF($C7=0,"",DIARIO!$A3) -> 2026-001 | B7: =IF($C7=0,"",DIARIO!$B3) -> 46038.445 | C7: =IF(AND($R7="Sí",DIARIO!$H3=$B$2),N(DIARIO!$I3),0) -> 0.5 | D7: =IF($C7=0,0,N(DIARIO!$L3)+IF(DIARIO!$K3="EUR",N(DIARIO!$J3),0)) -> 20030 | E7: =IF($C7=0,0,$D7/$C7) -> 40060 | F7: =IF($C7=0,"",$T7) -> 0.5 | G7: =IF($C7=0,"",MAX(0,MIN($C7,$E$4-($T7-$C7)))) -> 0 | H7: =IF($C7=0,"",$C7-$G7) -> 0.5 | J7: =IF($L7=0,"",DIARIO!$A3) | K7: =IF($L7=0,"",DIARIO!$B3) | L7: =IF(AND($S7="Sí",DIARIO!$F3=$B$2),N(DIARIO!$G3),0) -> 0 | M7: =IF($L7=0,"",$U7) | N7: =IF($L7=0,"",SUMPRODUCT($E$7:$E$106*((((($U7-($T$7:$T$106-$C$7:$C$106))+ABS(($U7-($T$7:$T$106-$C$7:$C$106))))/2)+$C$7:$C$106-ABS(((($U7-($T$7:$T$106-$C$7:$C$106))+ABS(($U7-($T$7:$T$106-$C$7:$C$106))))/2)-$C$7:$C$106))/2))-SUMPRODUCT($E$7:$E$106*(((((($U7-$L7)-($T$7:$T$106-$C$7:$C$106))+ABS((($U7-$L7)-($T$7:$T$106-$C$7:$C$106))))/2)+$C$7:$C$106-ABS((((($U7-$L7)-($T$7:$T$106-$C$7:$C$106))+ABS((($U7-$L7)-($T$7:$T$106-$C$7:$C$106))))/2)-$C$7:$C$106))/2))) | O7: =IF($L7=0,"",N(DIARIO!$L3)-IF(DIARIO!$K3="EUR",N(DIARIO!$J3),0)) | P7: =IF($L7=0,"",$O7-$N7) | R7: =IF(DIARIO!$C3="","",IFERROR(INDEX(PARÁMETROS!$D$5:$D$15,MATCH(DIARIO!$C3,PARÁMETROS!$A$5:$A$15,0)),"")) -> Sí | S7: =IF(DIARIO!$C3="","",IFERROR(INDEX(PARÁMETROS!$E$5:$E$15,MATCH(DIARIO!$C3,PARÁMETROS!$A$5:$A$15,0)),"")) -> No | T7: =SUM($C$7:$C7) -> 0.5 | U7: =SUM($L$7:$L7) -> 0
A8: =IF($C8=0,"",DIARIO!$A4) | B8: =IF($C8=0,"",DIARIO!$B4) | C8: =IF(AND($R8="Sí",DIARIO!$H4=$B$2),N(DIARIO!$I4),0) -> 0 | D8: =IF($C8=0,0,N(DIARIO!$L4)+IF(DIARIO!$K4="EUR",N(DIARIO!$J4),0)) -> 0 | E8: =IF($C8=0,0,$D8/$C8) -> 0 | F8: =IF($C8=0,"",$T8) | G8: =IF($C8=0,"",MAX(0,MIN($C8,$E$4-($T8-$C8)))) | H8: =IF($C8=0,"",$C8-$G8) | J8: =IF($L8=0,"",DIARIO!$A4) | K8: =IF($L8=0,"",DIARIO!$B4) | L8: =IF(AND($S8="Sí",DIARIO!$F4=$B$2),N(DIARIO!$G4),0) -> 0 | M8: =IF($L8=0,"",$U8) | N8: =IF($L8=0,"",SUMPRODUCT($E$7:$E$106*((((($U8-($T$7:$T$106-$C$7:$C$106))+ABS(($U8-($T$7:$T$106-$C$7:$C$106))))/2)+$C$7:$C$106-ABS(((($U8-($T$7:$T$106-$C$7:$C$106))+ABS(($U8-($T$7:$T$106-$C$7:$C$106))))/2)-$C$7:$C$106))/2))-SUMPRODUCT($E$7:$E$106*(((((($U8-$L8)-($T$7:$T$106-$C$7:$C$106))+ABS((($U8-$L8)-($T$7:$T$106-$C$7:$C$106))))/2)+$C$7:$C$106-ABS((((($U8-$L8)-($T$7:$T$106-$C$7:$C$106))+ABS((($U8-$L8)-($T$7:$T$106-$C$7:$C$106))))/2)-$C$7:$C$106))/2))) | O8: =IF($L8=0,"",N(DIARIO!$L4)-IF(DIARIO!$K4="EUR",N(DIARIO!$J4),0)) | P8: =IF($L8=0,"",$O8-$N8) | R8: =IF(DIARIO!$C4="","",IFERROR(INDEX(PARÁMETROS!$D$5:$D$15,MATCH(DIARIO!$C4,PARÁMETROS!$A$5:$A$15,0)),"")) -> No | S8: =IF(DIARIO!$C4="","",IFERROR(INDEX(PARÁMETROS!$E$5:$E$15,MATCH(DIARIO!$C4,PARÁMETROS!$A$5:$A$15,0)),"")) -> No | T8: =SUM($C$7:$C8) -> 0.5 | U8: =SUM($L$7:$L8) -> 0
A9: =IF($C9=0,"",DIARIO!$A5) -> 2026-003 | B9: =IF($C9=0,"",DIARIO!$B5) -> 46082.383 | C9: =IF(AND($R9="Sí",DIARIO!$H5=$B$2),N(DIARIO!$I5),0) -> 0.05 | D9: =IF($C9=0,0,N(DIARIO!$L5)+IF(DIARIO!$K5="EUR",N(DIARIO!$J5),0)) -> 130 | E9: =IF($C9=0,0,$D9/$C9) -> 2600 | F9: =IF($C9=0,"",$T9) -> 0.55 | G9: =IF($C9=0,"",MAX(0,MIN($C9,$E$4-($T9-$C9)))) -> 0 | H9: =IF($C9=0,"",$C9-$G9) -> 0.05 | J9: =IF($L9=0,"",DIARIO!$A5) | K9: =IF($L9=0,"",DIARIO!$B5) | L9: =IF(AND($S9="Sí",DIARIO!$F5=$B$2),N(DIARIO!$G5),0) -> 0 | M9: =IF($L9=0,"",$U9) | N9: =IF($L9=0,"",SUMPRODUCT($E$7:$E$106*((((($U9-($T$7:$T$106-$C$7:$C$106))+ABS(($U9-($T$7:$T$106-$C$7:$C$106))))/2)+$C$7:$C$106-ABS(((($U9-($T$7:$T$106-$C$7:$C$106))+ABS(($U9-($T$7:$T$106-$C$7:$C$106))))/2)-$C$7:$C$106))/2))-SUMPRODUCT($E$7:$E$106*(((((($U9-$L9)-($T$7:$T$106-$C$7:$C$106))+ABS((($U9-$L9)-($T$7:$T$106-$C$7:$C$106))))/2)+$C$7:$C$106-ABS((((($U9-$L9)-($T$7:$T$106-$C$7:$C$106))+ABS((($U9-$L9)-($T$7:$T$106-$C$7:$C$106))))/2)-$C$7:$C$106))/2))) | O9: =IF($L9=0,"",N(DIARIO!$L5)-IF(DIARIO!$K5="EUR",N(DIARIO!$J5),0)) | P9: =IF($L9=0,"",$O9-$N9) | R9: =IF(DIARIO!$C5="","",IFERROR(INDEX(PARÁMETROS!$D$5:$D$15,MATCH(DIARIO!$C5,PARÁMETROS!$A$5:$A$15,0)),"")) -> Sí | S9: =IF(DIARIO!$C5="","",IFERROR(INDEX(PARÁMETROS!$E$5:$E$15,MATCH(DIARIO!$C5,PARÁMETROS!$A$5:$A$15,0)),"")) -> No | T9: =SUM($C$7:$C9) -> 0.55 | U9: =SUM($L$7:$L9) -> 0
A10: =IF($C10=0,"",DIARIO!$A6) | B10: =IF($C10=0,"",DIARIO!$B6) | C10: =IF(AND($R10="Sí",DIARIO!$H6=$B$2),N(DIARIO!$I6),0) -> 0 | D10: =IF($C10=0,0,N(DIARIO!$L6)+IF(DIARIO!$K6="EUR",N(DIARIO!$J6),0)) -> 0 | E10: =IF($C10=0,0,$D10/$C10) -> 0 | F10: =IF($C10=0,"",$T10) | G10: =IF($C10=0,"",MAX(0,MIN($C10,$E$4-($T10-$C10)))) | H10: =IF($C10=0,"",$C10-$G10) | J10: =IF($L10=0,"",DIARIO!$A6) | K10: =IF($L10=0,"",DIARIO!$B6) | L10: =IF(AND($S10="Sí",DIARIO!$F6=$B$2),N(DIARIO!$G6),0) -> 0 | M10: =IF($L10=0,"",$U10) | N10: =IF($L10=0,"",SUMPRODUCT($E$7:$E$106*((((($U10-($T$7:$T$106-$C$7:$C$106))+ABS(($U10-($T$7:$T$106-$C$7:$C$106))))/2)+$C$7:$C$106-ABS(((($U10-($T$7:$T$106-$C$7:$C$106))+ABS(($U10-($T$7:$T$106-$C$7:$C$106))))/2)-$C$7:$C$106))/2))-SUMPRODUCT($E$7:$E$106*(((((($U10-$L10)-($T$7:$T$106-$C$7:$C$106))+ABS((($U10-$L10)-($T$7:$T$106-$C$7:$C$106))))/2)+$C$7:$C$106-ABS((((($U10-$L10)-($T$7:$T$106-$C$7:$C$106))+ABS((($U10-$L10)-($T$7:$T$106-$C$7:$C$106))))/2)-$C$7:$C$106))/2))) | O10: =IF($L10=0,"",N(DIARIO!$L6)-IF(DIARIO!$K6="EUR",N(DIARIO!$J6),0)) | P10: =IF($L10=0,"",$O10-$N10) | R10: =IF(DIARIO!$C6="","",IFERROR(INDEX(PARÁMETROS!$D$5:$D$15,MATCH(DIARIO!$C6,PARÁMETROS!$A$5:$A$15,0)),"")) | S10: =IF(DIARIO!$C6="","",IFERROR(INDEX(PARÁMETROS!$E$5:$E$15,MATCH(DIARIO!$C6,PARÁMETROS!$A$5:$A$15,0)),"")) | T10: =SUM($C$7:$C10) -> 0.55 | U10: =SUM($L$7:$L10) -> 0
A11: =IF($C11=0,"",DIARIO!$A7) | B11: =IF($C11=0,"",DIARIO!$B7) | C11: =IF(AND($R11="Sí",DIARIO!$H7=$B$2),N(DIARIO!$I7),0) -> 0 | D11: =IF($C11=0,0,N(DIARIO!$L7)+IF(DIARIO!$K7="EUR",N(DIARIO!$J7),0)) -> 0 | E11: =IF($C11=0,0,$D11/$C11) -> 0 | F11: =IF($C11=0,"",$T11) | G11: =IF($C11=0,"",MAX(0,MIN($C11,$E$4-($T11-$C11)))) | H11: =IF($C11=0,"",$C11-$G11) | J11: =IF($L11=0,"",DIARIO!$A7) | K11: =IF($L11=0,"",DIARIO!$B7) | L11: =IF(AND($S11="Sí",DIARIO!$F7=$B$2),N(DIARIO!$G7),0) -> 0 | M11: =IF($L11=0,"",$U11) | N11: =IF($L11=0,"",SUMPRODUCT($E$7:$E$106*((((($U11-($T$7:$T$106-$C$7:$C$106))+ABS(($U11-($T$7:$T$106-$C$7:$C$106))))/2)+$C$7:$C$106-ABS(((($U11-($T$7:$T$106-$C$7:$C$106))+ABS(($U11-($T$7:$T$106-$C$7:$C$106))))/2)-$C$7:$C$106))/2))-SUMPRODUCT($E$7:$E$106*(((((($U11-$L11)-($T$7:$T$106-$C$7:$C$106))+ABS((($U11-$L11)-($T$7:$T$106-$C$7:$C$106))))/2)+$C$7:$C$106-ABS((((($U11-$L11)-($T$7:$T$106-$C$7:$C$106))+ABS((($U11-$L11)-($T$7:$T$106-$C$7:$C$106))))/2)-$C$7:$C$106))/2))) | O11: =IF($L11=0,"",N(DIARIO!$L7)-IF(DIARIO!$K7="EUR",N(DIARIO!$J7),0)) | P11: =IF($L11=0,"",$O11-$N11) | R11: =IF(DIARIO!$C7="","",IFERROR(INDEX(PARÁMETROS!$D$5:$D$15,MATCH(DIARIO!$C7,PARÁMETROS!$A$5:$A$15,0)),"")) | S11: =IF(DIARIO!$C7="","",IFERROR(INDEX(PARÁMETROS!$E$5:$E$15,MATCH(DIARIO!$C7,PARÁMETROS!$A$5:$A$15,0)),"")) | T11: =SUM($C$7:$C11) -> 0.55 | U11: =SUM($L$7:$L11) -> 0
A12: =IF($C12=0,"",DIARIO!$A8) | B12: =IF($C12=0,"",DIARIO!$B8) | C12: =IF(AND($R12="Sí",DIARIO!$H8=$B$2),N(DIARIO!$I8),0) -> 0 | D12: =IF($C12=0,0,N(DIARIO!$L8)+IF(DIARIO!$K8="EUR",N(DIARIO!$J8),0)) -> 0 | E12: =IF($C12=0,0,$D12/$C12) -> 0 | F12: =IF($C12=0,"",$T12) | G12: =IF($C12=0,"",MAX(0,MIN($C12,$E$4-($T12-$C12)))) | H12: =IF($C12=0,"",$C12-$G12) | J12: =IF($L12=0,"",DIARIO!$A8) | K12: =IF($L12=0,"",DIARIO!$B8) | L12: =IF(AND($S12="Sí",DIARIO!$F8=$B$2),N(DIARIO!$G8),0) -> 0 | M12: =IF($L12=0,"",$U12) | N12: =IF($L12=0,"",SUMPRODUCT($E$7:$E$106*((((($U12-($T$7:$T$106-$C$7:$C$106))+ABS(($U12-($T$7:$T$106-$C$7:$C$106))))/2)+$C$7:$C$106-ABS(((($U12-($T$7:$T$106-$C$7:$C$106))+ABS(($U12-($T$7:$T$106-$C$7:$C$106))))/2)-$C$7:$C$106))/2))-SUMPRODUCT($E$7:$E$106*(((((($U12-$L12)-($T$7:$T$106-$C$7:$C$106))+ABS((($U12-$L12)-($T$7:$T$106-$C$7:$C$106))))/2)+$C$7:$C$106-ABS((((($U12-$L12)-($T$7:$T$106-$C$7:$C$106))+ABS((($U12-$L12)-($T$7:$T$106-$C$7:$C$106))))/2)-$C$7:$C$106))/2))) | O12: =IF($L12=0,"",N(DIARIO!$L8)-IF(DIARIO!$K8="EUR",N(DIARIO!$J8),0)) | P12: =IF($L12=0,"",$O12-$N12) | R12: =IF(DIARIO!$C8="","",IFERROR(INDEX(PARÁMETROS!$D$5:$D$15,MATCH(DIARIO!$C8,PARÁMETROS!$A$5:$A$15,0)),"")) | S12: =IF(DIARIO!$C8="","",IFERROR(INDEX(PARÁMETROS!$E$5:$E$15,MATCH(DIARIO!$C8,PARÁMETROS!$A$5:$A$15,0)),"")) | T12: =SUM($C$7:$C12) -> 0.55 | U12: =SUM($L$7:$L12) -> 0
A13: =IF($C13=0,"",DIARIO!$A9) | B13: =IF($C13=0,"",DIARIO!$B9) | C13: =IF(AND($R13="Sí",DIARIO!$H9=$B$2),N(DIARIO!$I9),0) -> 0 | D13: =IF($C13=0,0,N(DIARIO!$L9)+IF(DIARIO!$K9="EUR",N(DIARIO!$J9),0)) -> 0 | E13: =IF($C13=0,0,$D13/$C13) -> 0 | F13: =IF($C13=0,"",$T13) | G13: =IF($C13=0,"",MAX(0,MIN($C13,$E$4-($T13-$C13)))) | H13: =IF($C13=0,"",$C13-$G13) | J13: =IF($L13=0,"",DIARIO!$A9) | K13: =IF($L13=0,"",DIARIO!$B9) | L13: =IF(AND($S13="Sí",DIARIO!$F9=$B$2),N(DIARIO!$G9),0) -> 0 | M13: =IF($L13=0,"",$U13) | N13: =IF($L13=0,"",SUMPRODUCT($E$7:$E$106*((((($U13-($T$7:$T$106-$C$7:$C$106))+ABS(($U13-($T$7:$T$106-$C$7:$C$106))))/2)+$C$7:$C$106-ABS(((($U13-($T$7:$T$106-$C$7:$C$106))+ABS(($U13-($T$7:$T$106-$C$7:$C$106))))/2)-$C$7:$C$106))/2))-SUMPRODUCT($E$7:$E$106*(((((($U13-$L13)-($T$7:$T$106-$C$7:$C$106))+ABS((($U13-$L13)-($T$7:$T$106-$C$7:$C$106))))/2)+$C$7:$C$106-ABS((((($U13-$L13)-($T$7:$T$106-$C$7:$C$106))+ABS((($U13-$L13)-($T$7:$T$106-$C$7:$C$106))))/2)-$C$7:$C$106))/2))) | O13: =IF($L13=0,"",N(DIARIO!$L9)-IF(DIARIO!$K9="EUR",N(DIARIO!$J9),0)) | P13: =IF($L13=0,"",$O13-$N13) | R13: =IF(DIARIO!$C9="","",IFERROR(INDEX(PARÁMETROS!$D$5:$D$15,MATCH(DIARIO!$C9,PARÁMETROS!$A$5:$A$15,0)),"")) | S13: =IF(DIARIO!$C9="","",IFERROR(INDEX(PARÁMETROS!$E$5:$E$15,MATCH(DIARIO!$C9,PARÁMETROS!$A$5:$A$15,0)),"")) | T13: =SUM($C$7:$C13) -> 0.55 | U13: =SUM($L$7:$L13) -> 0
A14: =IF($C14=0,"",DIARIO!$A10) | B14: =IF($C14=0,"",DIARIO!$B10) | C14: =IF(AND($R14="Sí",DIARIO!$H10=$B$2),N(DIARIO!$I10),0) -> 0 | D14: =IF($C14=0,0,N(DIARIO!$L10)+IF(DIARIO!$K10="EUR",N(DIARIO!$J10),0)) -> 0 | E14: =IF($C14=0,0,$D14/$C14) -> 0 | F14: =IF($C14=0,"",$T14) | G14: =IF($C14=0,"",MAX(0,MIN($C14,$E$4-($T14-$C14)))) | H14: =IF($C14=0,"",$C14-$G14) | J14: =IF($L14=0,"",DIARIO!$A10) | K14: =IF($L14=0,"",DIARIO!$B10) | L14: =IF(AND($S14="Sí",DIARIO!$F10=$B$2),N(DIARIO!$G10),0) -> 0 | M14: =IF($L14=0,"",$U14) | N14: =IF($L14=0,"",SUMPRODUCT($E$7:$E$106*((((($U14-($T$7:$T$106-$C$7:$C$106))+ABS(($U14-($T$7:$T$106-$C$7:$C$106))))/2)+$C$7:$C$106-ABS(((($U14-($T$7:$T$106-$C$7:$C$106))+ABS(($U14-($T$7:$T$106-$C$7:$C$106))))/2)-$C$7:$C$106))/2))-SUMPRODUCT($E$7:$E$106*(((((($U14-$L14)-($T$7:$T$106-$C$7:$C$106))+ABS((($U14-$L14)-($T$7:$T$106-$C$7:$C$106))))/2)+$C$7:$C$106-ABS((((($U14-$L14)-($T$7:$T$106-$C$7:$C$106))+ABS((($U14-$L14)-($T$7:$T$106-$C$7:$C$106))))/2)-$C$7:$C$106))/2))) | O14: =IF($L14=0,"",N(DIARIO!$L10)-IF(DIARIO!$K10="EUR",N(DIARIO!$J10),0)) | P14: =IF($L14=0,"",$O14-$N14) | R14: =IF(DIARIO!$C10="","",IFERROR(INDEX(PARÁMETROS!$D$5:$D$15,MATCH(DIARIO!$C10,PARÁMETROS!$A$5:$A$15,0)),"")) | S14: =IF(DIARIO!$C10="","",IFERROR(INDEX(PARÁMETROS!$E$5:$E$15,MATCH(DIARIO!$C10,PARÁMETROS!$A$5:$A$15,0)),"")) | T14: =SUM($C$7:$C14) -> 0.55 | U14: =SUM($L$7:$L14) -> 0
A15: =IF($C15=0,"",DIARIO!$A11) | B15: =IF($C15=0,"",DIARIO!$B11) | C15: =IF(AND($R15="Sí",DIARIO!$H11=$B$2),N(DIARIO!$I11),0) -> 0 | D15: =IF($C15=0,0,N(DIARIO!$L11)+IF(DIARIO!$K11="EUR",N(DIARIO!$J11),0)) -> 0 | E15: =IF($C15=0,0,$D15/$C15) -> 0 | F15: =IF($C15=0,"",$T15) | G15: =IF($C15=0,"",MAX(0,MIN($C15,$E$4-($T15-$C15)))) | H15: =IF($C15=0,"",$C15-$G15) | J15: =IF($L15=0,"",DIARIO!$A11) | K15: =IF($L15=0,"",DIARIO!$B11) | L15: =IF(AND($S15="Sí",DIARIO!$F11=$B$2),N(DIARIO!$G11),0) -> 0 | M15: =IF($L15=0,"",$U15) | N15: =IF($L15=0,"",SUMPRODUCT($E$7:$E$106*((((($U15-($T$7:$T$106-$C$7:$C$106))+ABS(($U15-($T$7:$T$106-$C$7:$C$106))))/2)+$C$7:$C$106-ABS(((($U15-($T$7:$T$106-$C$7:$C$106))+ABS(($U15-($T$7:$T$106-$C$7:$C$106))))/2)-$C$7:$C$106))/2))-SUMPRODUCT($E$7:$E$106*(((((($U15-$L15)-($T$7:$T$106-$C$7:$C$106))+ABS((($U15-$L15)-($T$7:$T$106-$C$7:$C$106))))/2)+$C$7:$C$106-ABS((((($U15-$L15)-($T$7:$T$106-$C$7:$C$106))+ABS((($U15-$L15)-($T$7:$T$106-$C$7:$C$106))))/2)-$C$7:$C$106))/2))) | O15: =IF($L15=0,"",N(DIARIO!$L11)-IF(DIARIO!$K11="EUR",N(DIARIO!$J11),0)) | P15: =IF($L15=0,"",$O15-$N15) | R15: =IF(DIARIO!$C11="","",IFERROR(INDEX(PARÁMETROS!$D$5:$D$15,MATCH(DIARIO!$C11,PARÁMETROS!$A$5:$A$15,0)),"")) | S15: =IF(DIARIO!$C11="","",IFERROR(INDEX(PARÁMETROS!$E$5:$E$15,MATCH(DIARIO!$C11,PARÁMETROS!$A$5:$A$15,0)),"")) | T15: =SUM($C$7:$C15) -> 0.55 | U15: =SUM($L$7:$L15) -> 0
A16: =IF($C16=0,"",DIARIO!$A12) | B16: =IF($C16=0,"",DIARIO!$B12) | C16: =IF(AND($R16="Sí",DIARIO!$H12=$B$2),N(DIARIO!$I12),0) -> 0 | D16: =IF($C16=0,0,N(DIARIO!$L12)+IF(DIARIO!$K12="EUR",N(DIARIO!$J12),0)) -> 0 | E16: =IF($C16=0,0,$D16/$C16) -> 0 | F16: =IF($C16=0,"",$T16) | G16: =IF($C16=0,"",MAX(0,MIN($C16,$E$4-($T16-$C16)))) | H16: =IF($C16=0,"",$C16-$G16) | J16: =IF($L16=0,"",DIARIO!$A12) | K16: =IF($L16=0,"",DIARIO!$B12) | L16: =IF(AND($S16="Sí",DIARIO!$F12=$B$2),N(DIARIO!$G12),0) -> 0 | M16: =IF($L16=0,"",$U16) | N16: =IF($L16=0,"",SUMPRODUCT($E$7:$E$106*((((($U16-($T$7:$T$106-$C$7:$C$106))+ABS(($U16-($T$7:$T$106-$C$7:$C$106))))/2)+$C$7:$C$106-ABS(((($U16-($T$7:$T$106-$C$7:$C$106))+ABS(($U16-($T$7:$T$106-$C$7:$C$106))))/2)-$C$7:$C$106))/2))-SUMPRODUCT($E$7:$E$106*(((((($U16-$L16)-($T$7:$T$106-$C$7:$C$106))+ABS((($U16-$L16)-($T$7:$T$106-$C$7:$C$106))))/2)+$C$7:$C$106-ABS((((($U16-$L16)-($T$7:$T$106-$C$7:$C$106))+ABS((($U16-$L16)-($T$7:$T$106-$C$7:$C$106))))/2)-$C$7:$C$106))/2))) | O16: =IF($L16=0,"",N(DIARIO!$L12)-IF(DIARIO!$K12="EUR",N(DIARIO!$J12),0)) | P16: =IF($L16=0,"",$O16-$N16) | R16: =IF(DIARIO!$C12="","",IFERROR(INDEX(PARÁMETROS!$D$5:$D$15,MATCH(DIARIO!$C12,PARÁMETROS!$A$5:$A$15,0)),"")) | S16: =IF(DIARIO!$C12="","",IFERROR(INDEX(PARÁMETROS!$E$5:$E$15,MATCH(DIARIO!$C12,PARÁMETROS!$A$5:$A$15,0)),"")) | T16: =SUM($C$7:$C16) -> 0.55 | U16: =SUM($L$7:$L16) -> 0
A17: =IF($C17=0,"",DIARIO!$A13) | B17: =IF($C17=0,"",DIARIO!$B13) | C17: =IF(AND($R17="Sí",DIARIO!$H13=$B$2),N(DIARIO!$I13),0) -> 0 | D17: =IF($C17=0,0,N(DIARIO!$L13)+IF(DIARIO!$K13="EUR",N(DIARIO!$J13),0)) -> 0 | E17: =IF($C17=0,0,$D17/$C17) -> 0 | F17: =IF($C17=0,"",$T17) | G17: =IF($C17=0,"",MAX(0,MIN($C17,$E$4-($T17-$C17)))) | H17: =IF($C17=0,"",$C17-$G17) | J17: =IF($L17=0,"",DIARIO!$A13) | K17: =IF($L17=0,"",DIARIO!$B13) | L17: =IF(AND($S17="Sí",DIARIO!$F13=$B$2),N(DIARIO!$G13),0) -> 0 | M17: =IF($L17=0,"",$U17) | N17: =IF($L17=0,"",SUMPRODUCT($E$7:$E$106*((((($U17-($T$7:$T$106-$C$7:$C$106))+ABS(($U17-($T$7:$T$106-$C$7:$C$106))))/2)+$C$7:$C$106-ABS(((($U17-($T$7:$T$106-$C$7:$C$106))+ABS(($U17-($T$7:$T$106-$C$7:$C$106))))/2)-$C$7:$C$106))/2))-SUMPRODUCT($E$7:$E$106*(((((($U17-$L17)-($T$7:$T$106-$C$7:$C$106))+ABS((($U17-$L17)-($T$7:$T$106-$C$7:$C$106))))/2)+$C$7:$C$106-ABS((((($U17-$L17)-($T$7:$T$106-$C$7:$C$106))+ABS((($U17-$L17)-($T$7:$T$106-$C$7:$C$106))))/2)-$C$7:$C$106))/2))) | O17: =IF($L17=0,"",N(DIARIO!$L13)-IF(DIARIO!$K13="EUR",N(DIARIO!$J13),0)) | P17: =IF($L17=0,"",$O17-$N17) | R17: =IF(DIARIO!$C13="","",IFERROR(INDEX(PARÁMETROS!$D$5:$D$15,MATCH(DIARIO!$C13,PARÁMETROS!$A$5:$A$15,0)),"")) | S17: =IF(DIARIO!$C13="","",IFERROR(INDEX(PARÁMETROS!$E$5:$E$15,MATCH(DIARIO!$C13,PARÁMETROS!$A$5:$A$15,0)),"")) | T17: =SUM($C$7:$C17) -> 0.55 | U17: =SUM($L$7:$L17) -> 0
A18: =IF($C18=0,"",DIARIO!$A14) | B18: =IF($C18=0,"",DIARIO!$B14) | C18: =IF(AND($R18="Sí",DIARIO!$H14=$B$2),N(DIARIO!$I14),0) -> 0 | D18: =IF($C18=0,0,N(DIARIO!$L14)+IF(DIARIO!$K14="EUR",N(DIARIO!$J14),0)) -> 0 | E18: =IF($C18=0,0,$D18/$C18) -> 0 | F18: =IF($C18=0,"",$T18) | G18: =IF($C18=0,"",MAX(0,MIN($C18,$E$4-($T18-$C18)))) | H18: =IF($C18=0,"",$C18-$G18) | J18: =IF($L18=0,"",DIARIO!$A14) | K18: =IF($L18=0,"",DIARIO!$B14) | L18: =IF(AND($S18="Sí",DIARIO!$F14=$B$2),N(DIARIO!$G14),0) -> 0 | M18: =IF($L18=0,"",$U18) | N18: =IF($L18=0,"",SUMPRODUCT($E$7:$E$106*((((($U18-($T$7:$T$106-$C$7:$C$106))+ABS(($U18-($T$7:$T$106-$C$7:$C$106))))/2)+$C$7:$C$106-ABS(((($U18-($T$7:$T$106-$C$7:$C$106))+ABS(($U18-($T$7:$T$106-$C$7:$C$106))))/2)-$C$7:$C$106))/2))-SUMPRODUCT($E$7:$E$106*(((((($U18-$L18)-($T$7:$T$106-$C$7:$C$106))+ABS((($U18-$L18)-($T$7:$T$106-$C$7:$C$106))))/2)+$C$7:$C$106-ABS((((($U18-$L18)-($T$7:$T$106-$C$7:$C$106))+ABS((($U18-$L18)-($T$7:$T$106-$C$7:$C$106))))/2)-$C$7:$C$106))/2))) | O18: =IF($L18=0,"",N(DIARIO!$L14)-IF(DIARIO!$K14="EUR",N(DIARIO!$J14),0)) | P18: =IF($L18=0,"",$O18-$N18) | R18: =IF(DIARIO!$C14="","",IFERROR(INDEX(PARÁMETROS!$D$5:$D$15,MATCH(DIARIO!$C14,PARÁMETROS!$A$5:$A$15,0)),"")) | S18: =IF(DIARIO!$C14="","",IFERROR(INDEX(PARÁMETROS!$E$5:$E$15,MATCH(DIARIO!$C14,PARÁMETROS!$A$5:$A$15,0)),"")) | T18: =SUM($C$7:$C18) -> 0.55 | U18: =SUM($L$7:$L18) -> 0
... A106: =IF($C106=0,"",DIARIO!$A102) | B106: =IF($C106=0,"",DIARIO!$B102) | C106: =IF(AND($R106="Sí",DIARIO!$H102=$B$2),N(DIARIO!$I102),0) -> 0 | D106: =IF($C106=0,0,N(DIARIO!$L102)+IF(DIARIO!$K102="EUR",N(DIARIO!$J102),0)) -> 0 | E106: =IF($C106=0,0,$D106/$C106) -> 0 | F106: =IF($C106=0,"",$T106) | G106: =IF($C106=0,"",MAX(0,MIN($C106,$E$4-($T106-$C106)))) | H106: =IF($C106=0,"",$C106-$G106) | J106: =IF($L106=0,"",DIARIO!$A102) | K106: =IF($L106=0,"",DIARIO!$B102) | L106: =IF(AND($S106="Sí",DIARIO!$F102=$B$2),N(DIARIO!$G102),0) -> 0 | M106: =IF($L106=0,"",$U106) | N106: =IF($L106=0,"",SUMPRODUCT($E$7:$E$106*((((($U106-($T$7:$T$106-$C$7:$C$106))+ABS(($U106-($T$7:$T$106-$C$7:$C$106))))/2)+$C$7:$C$106-ABS(((($U106-($T$7:$T$106-$C$7:$C$106))+ABS(($U106-($T$7:$T$106-$C$7:$C$106))))/2)-$C$7:$C$106))/2))-SUMPRODUCT($E$7:$E$106*(((((($U106-$L106)-($T$7:$T$106-$C$7:$C$106))+ABS((($U106-$L106)-($T$7:$T$106-$C$7:$C$106))))/2)+$C$7:$C$106-ABS((((($U106-$L106)-($T$7:$T$106-$C$7:$C$106))+ABS((($U106-$L106)-($T$7:$T$106-$C$7:$C$106))))/2)-$C$7:$C$106))/2))) | O106: =IF($L106=0,"",N(DIARIO!$L102)-IF(DIARIO!$K102="EUR",N(DIARIO!$J102),0)) | P106: =IF($L106=0,"",$O106-$N106) | R106: =IF(DIARIO!$C102="","",IFERROR(INDEX(PARÁMETROS!$D$5:$D$15,MATCH(DIARIO!$C102,PARÁMETROS!$A$5:$A$15,0)),"")) | S106: =IF(DIARIO!$C102="","",IFERROR(INDEX(PARÁMETROS!$E$5:$E$15,MATCH(DIARIO!$C102,PARÁMETROS!$A$5:$A$15,0)),"")) | T106: =SUM($C$7:$C106) -> 0.55 | U106: =SUM($L$7:$L106) -> 0

Sheet CUADRE
A1: CUADRE — se calcula solo. Saldo calculado frente a saldo real declarado, con semáforo (Unidad 5, Tabla 5)
A2: Fecha de corte (la de SALDOS): | B2: =SALDOS!$B$2 -> 46387 | C2: Semáforo: |dif| ≤ tolerancia verde → OK · ≤ tolerancia ámbar → REVISAR · mayor → ERROR (tolerancias configurables en PARÁMETROS). Amarillo = teclear el saldo que muestra la fuente real.
A3: Ubicación | B3: Activo | C3: Saldo calculado | D3: Saldo real declarado | E3: Diferencia | F3: Estado | G3: Notas
A4: =IF(SALDOS!A5="","",SALDOS!A5) -> Exchange-A | B4: =IF(SALDOS!A5="","",SALDOS!B5) -> BTC | C4: =IF($A4="","",SALDOS!F5) -> 0.2498 | D4: 0.2498 | E4: =IF(OR($A4="",$D4=""),"",$D4-$C4) -> 0 | F4: =IF(OR($A4="",$D4=""),"",IF(ABS($E4)<=PARÁMETROS!$B$32,"OK",IF(ABS($E4)<=PARÁMETROS!$B$33,"REVISAR","ERROR"))) -> OK | G4: EJEMPLO — borrar
A5: =IF(SALDOS!A6="","",SALDOS!A6) -> Exchange-A | B5: =IF(SALDOS!A6="","",SALDOS!B6) -> EUR | C5: =IF($A5="","",SALDOS!F6) -> -20030 | E5: =IF(OR($A5="",$D5=""),"",$D5-$C5) | F5: =IF(OR($A5="",$D5=""),"",IF(ABS($E5)<=PARÁMETROS!$B$32,"OK",IF(ABS($E5)<=PARÁMETROS!$B$33,"REVISAR","ERROR")))
A6: =IF(SALDOS!A7="","",SALDOS!A7) | B6: =IF(SALDOS!A7="","",SALDOS!B7) | C6: =IF($A6="","",SALDOS!F7) | E6: =IF(OR($A6="",$D6=""),"",$D6-$C6) | F6: =IF(OR($A6="",$D6=""),"",IF(ABS($E6)<=PARÁMETROS!$B$32,"OK",IF(ABS($E6)<=PARÁMETROS!$B$33,"REVISAR","ERROR")))
A7: =IF(SALDOS!A8="","",SALDOS!A8) | B7: =IF(SALDOS!A8="","",SALDOS!B8) | C7: =IF($A7="","",SALDOS!F8) | E7: =IF(OR($A7="",$D7=""),"",$D7-$C7) | F7: =IF(OR($A7="",$D7=""),"",IF(ABS($E7)<=PARÁMETROS!$B$32,"OK",IF(ABS($E7)<=PARÁMETROS!$B$33,"REVISAR","ERROR")))
A8: =IF(SALDOS!A9="","",SALDOS!A9) | B8: =IF(SALDOS!A9="","",SALDOS!B9) | C8: =IF($A8="","",SALDOS!F9) | E8: =IF(OR($A8="",$D8=""),"",$D8-$C8) | F8: =IF(OR($A8="",$D8=""),"",IF(ABS($E8)<=PARÁMETROS!$B$32,"OK",IF(ABS($E8)<=PARÁMETROS!$B$33,"REVISAR","ERROR")))
A9: =IF(SALDOS!A10="","",SALDOS!A10) -> Wallet-Fría | B9: =IF(SALDOS!A10="","",SALDOS!B10) -> BTC | C9: =IF($A9="","",SALDOS!F10) -> 0.3 | D9: 0.2998 | E9: =IF(OR($A9="",$D9=""),"",$D9-$C9) -> -0.0002 | F9: =IF(OR($A9="",$D9=""),"",IF(ABS($E9)<=PARÁMETROS!$B$32,"OK",IF(ABS($E9)<=PARÁMETROS!$B$33,"REVISAR","ERROR"))) -> REVISAR | G9: EJEMPLO — borrar · descuadre de 0,0002: comisión embebida (Unidad 5, Tabla 6)
A10: =IF(SALDOS!A11="","",SALDOS!A11) -> Wallet-Fría | B10: =IF(SALDOS!A11="","",SALDOS!B11) -> EUR | C10: =IF($A10="","",SALDOS!F11) -> 0 | E10: =IF(OR($A10="",$D10=""),"",$D10-$C10) | F10: =IF(OR($A10="",$D10=""),"",IF(ABS($E10)<=PARÁMETROS!$B$32,"OK",IF(ABS($E10)<=PARÁMETROS!$B$33,"REVISAR","ERROR")))
A11: =IF(SALDOS!A12="","",SALDOS!A12) | B11: =IF(SALDOS!A12="","",SALDOS!B12) | C11: =IF($A11="","",SALDOS!F12) | E11: =IF(OR($A11="",$D11=""),"",$D11-$C11) | F11: =IF(OR($A11="",$D11=""),"",IF(ABS($E11)<=PARÁMETROS!$B$32,"OK",IF(ABS($E11)<=PARÁMETROS!$B$33,"REVISAR","ERROR")))
A12: =IF(SALDOS!A13="","",SALDOS!A13) | B12: =IF(SALDOS!A13="","",SALDOS!B13) | C12: =IF($A12="","",SALDOS!F13) | E12: =IF(OR($A12="",$D12=""),"",$D12-$C12) | F12: =IF(OR($A12="",$D12=""),"",IF(ABS($E12)<=PARÁMETROS!$B$32,"OK",IF(ABS($E12)<=PARÁMETROS!$B$33,"REVISAR","ERROR")))
A13: =IF(SALDOS!A14="","",SALDOS!A14) | B13: =IF(SALDOS!A14="","",SALDOS!B14) | C13: =IF($A13="","",SALDOS!F14) | E13: =IF(OR($A13="",$D13=""),"",$D13-$C13) | F13: =IF(OR($A13="",$D13=""),"",IF(ABS($E13)<=PARÁMETROS!$B$32,"OK",IF(ABS($E13)<=PARÁMETROS!$B$33,"REVISAR","ERROR")))
A14: =IF(SALDOS!A15="","",SALDOS!A15) -> Canal-LN | B14: =IF(SALDOS!A15="","",SALDOS!B15) -> BTC | C14: =IF($A14="","",SALDOS!F15) -> 0 | E14: =IF(OR($A14="",$D14=""),"",$D14-$C14) | F14: =IF(OR($A14="",$D14=""),"",IF(ABS($E14)<=PARÁMETROS!$B$32,"OK",IF(ABS($E14)<=PARÁMETROS!$B$33,"REVISAR","ERROR")))
A15: =IF(SALDOS!A16="","",SALDOS!A16) -> Canal-LN | B15: =IF(SALDOS!A16="","",SALDOS!B16) -> EUR | C15: =IF($A15="","",SALDOS!F16) -> 0 | E15: =IF(OR($A15="",$D15=""),"",$D15-$C15) | F15: =IF(OR($A15="",$D15=""),"",IF(ABS($E15)<=PARÁMETROS!$B$32,"OK",IF(ABS($E15)<=PARÁMETROS!$B$33,"REVISAR","ERROR")))
A16: =IF(SALDOS!A17="","",SALDOS!A17) | B16: =IF(SALDOS!A17="","",SALDOS!B17) | C16: =IF($A16="","",SALDOS!F17) | E16: =IF(OR($A16="",$D16=""),"",$D16-$C16) | F16: =IF(OR($A16="",$D16=""),"",IF(ABS($E16)<=PARÁMETROS!$B$32,"OK",IF(ABS($E16)<=PARÁMETROS!$B$33,"REVISAR","ERROR")))
A17: =IF(SALDOS!A18="","",SALDOS!A18) | B17: =IF(SALDOS!A18="","",SALDOS!B18) | C17: =IF($A17="","",SALDOS!F18) | E17: =IF(OR($A17="",$D17=""),"",$D17-$C17) | F17: =IF(OR($A17="",$D17=""),"",IF(ABS($E17)<=PARÁMETROS!$B$32,"OK",IF(ABS($E17)<=PARÁMETROS!$B$33,"REVISAR","ERROR")))
A18: =IF(SALDOS!A19="","",SALDOS!A19) | B18: =IF(SALDOS!A19="","",SALDOS!B19) | C18: =IF($A18="","",SALDOS!F19) | E18: =IF(OR($A18="",$D18=""),"",$D18-$C18) | F18: =IF(OR($A18="",$D18=""),"",IF(ABS($E18)<=PARÁMETROS!$B$32,"OK",IF(ABS($E18)<=PARÁMETROS!$B$33,"REVISAR","ERROR")))
A19: =IF(SALDOS!A20="","",SALDOS!A20) | B19: =IF(SALDOS!A20="","",SALDOS!B20) | C19: =IF($A19="","",SALDOS!F20) | E19: =IF(OR($A19="",$D19=""),"",$D19-$C19) | F19: =IF(OR($A19="",$D19=""),"",IF(ABS($E19)<=PARÁMETROS!$B$32,"OK",IF(ABS($E19)<=PARÁMETROS!$B$33,"REVISAR","ERROR")))
A20: =IF(SALDOS!A21="","",SALDOS!A21) | B20: =IF(SALDOS!A21="","",SALDOS!B21) | C20: =IF($A20="","",SALDOS!F21) | E20: =IF(OR($A20="",$D20=""),"",$D20-$C20) | F20: =IF(OR($A20="",$D20=""),"",IF(ABS($E20)<=PARÁMETROS!$B$32,"OK",IF(ABS($E20)<=PARÁMETROS!$B$33,"REVISAR","ERROR")))
A21: =IF(SALDOS!A22="","",SALDOS!A22) | B21: =IF(SALDOS!A22="","",SALDOS!B22) | C21: =IF($A21="","",SALDOS!F22) | E21: =IF(OR($A21="",$D21=""),"",$D21-$C21) | F21: =IF(OR($A21="",$D21=""),"",IF(ABS($E21)<=PARÁMETROS!$B$32,"OK",IF(ABS($E21)<=PARÁMETROS!$B$33,"REVISAR","ERROR")))
... A53: =IF(SALDOS!A54="","",SALDOS!A54) | B53: =IF(SALDOS!A54="","",SALDOS!B54) | C53: =IF($A53="","",SALDOS!F54) | E53: =IF(OR($A53="",$D53=""),"",$D53-$C53) | F53: =IF(OR($A53="",$D53=""),"",IF(ABS($E53)<=PARÁMETROS!$B$32,"OK",IF(ABS($E53)<=PARÁMETROS!$B$33,"REVISAR","ERROR")))
